README.txt
setup.cfg
setup.py
django_awesome_snippets.egg-info/PKG-INFO
django_awesome_snippets.egg-info/SOURCES.txt
django_awesome_snippets.egg-info/dependency_links.txt
django_awesome_snippets.egg-info/entry_points.txt
django_awesome_snippets.egg-info/not-zip-safe
django_awesome_snippets.egg-info/requires.txt
django_awesome_snippets.egg-info/top_level.txt
docs/conf.py
snippets/__init__.py