Metadata-Version: 1.0
Name: django-awesome-snippets
Version: 0.3
Summary: A decorator to generate and cache html snippets
Home-page: http://django-awesome-snippets.rtfd.org
Author: Gael Pasgrimaud
Author-email: gael@gawel.org
License: MIT
Platform: UNKNOWN
